mvc/__init__.py
mvc/action_output.py
mvc/interaction.py
mvc/noise.py
mvc/parametric_function.py
mvc/preprocess.py
mvc/view.py
mvc/controllers/__init__.py
mvc/controllers/base_controller.py
mvc/controllers/ddpg.py
mvc/controllers/eval.py
mvc/controllers/ppo.py
mvc/controllers/sac.py
mvc/envs/__init__.py
mvc/envs/wrappers.py
mvc/logger/__init__.py
mvc/logger/base_adapter.py
mvc/logger/comet_ml_adapter.py
mvc/logger/tfboard_adapter.py
mvc/logger/visdom_adapter.py
mvc/misc/__init__.py
mvc/misc/assertion.py
mvc/misc/batch.py
mvc/models/__init__.py
mvc/models/buffer.py
mvc/models/rollout.py
mvc/models/metrics/__init__.py
mvc/models/metrics/base_metric.py
mvc/models/metrics/metric.py
mvc/models/metrics/metrics.py
mvc/models/metrics/queue_metric.py
mvc/models/networks/__init__.py
mvc/models/networks/base_network.py
mvc/models/networks/ddpg.py
mvc/models/networks/ppo.py
mvc/models/networks/sac.py
tests/controllers/__init__.py
tests/controllers/test_base_controller.py
tests/controllers/test_ddpg.py
tests/controllers/test_eval.py
tests/controllers/test_ppo.py
tests/controllers/test_sac.py
tests/misc/__init__.py
tests/misc/test_assertion.py
tests/misc/test_batch.py
tests/models/__init__.py
tests/models/test_buffer.py
tests/models/test_rollout.py
tests/models/metrics/__init__.py
tests/models/metrics/test_base_metric.py
tests/models/metrics/test_metric.py
tests/models/metrics/test_metrics.py
tests/models/metrics/test_queue_metric.py
tests/models/networks/__init__.py
tests/models/networks/test_base_network.py
tests/models/networks/test_ddpg.py
tests/models/networks/test_ppo.py
tests/models/networks/test_sac.py
mvc-1.1.2.dist-info/LICENSE
mvc-1.1.2.dist-info/METADATA
mvc-1.1.2.dist-info/WHEEL
mvc-1.1.2.dist-info/top_level.txt
mvc-1.1.2.dist-info/RECORD
