Metadata-Version: 2.1
Name: mvc
Version: 1.1.2
Summary: Cleanest Deep Reinforcement Learning Implementation Based on Web MVC
Home-page: https://github.com/takuseno/mvc-drl
Author: takuseno
Author-email: takuma.seno@gmail.com
License: MIT
Keywords: deep reinforcemtne learning,tensorflow
Platform: UNKNOWN
Classifier: License :: OSI Approved :: MIT License
Classifier: Programming Language :: Python :: 3.5
Classifier: Programming Language :: Python :: 3.6
Requires-Python: >=3.5
Requires-Dist: pytest (==3.8.1)
Requires-Dist: comet-ml (==1.0.44)
Requires-Dist: visdom (==0.1.8.6)
Requires-Dist: seaborn (==0.9.0)
Requires-Dist: matplotlib (==2.0.2)
Requires-Dist: pylint (==2.2.2)
Requires-Dist: pycodestyle (==2.4.0)
Requires-Dist: gym (==0.11.0)
Requires-Dist: coverage (==4.5.2)
